collectd_gnocchi/__init__.py
collectd_gnocchi-1.7.1.dist-info/DESCRIPTION.rst
collectd_gnocchi-1.7.1.dist-info/METADATA
collectd_gnocchi-1.7.1.dist-info/RECORD
collectd_gnocchi-1.7.1.dist-info/WHEEL
collectd_gnocchi-1.7.1.dist-info/metadata.json
collectd_gnocchi-1.7.1.dist-info/pbr.json
collectd_gnocchi-1.7.1.dist-info/top_level.txt
