Metadata-Version: 2.0
Name: collectd-gnocchi
Version: 1.7.1
Summary: Gnocchi storage plugin for collectd
Home-page: http://github.com/gnocchixyz/collectd-gnocchi
Author: Julien Danjou
Author-email: julien@danjou.info
License: UNKNOWN
Platform: UNKNOWN
Classifier: Intended Audience :: Information Technology
Classifier: Intended Audience :: System Administrators
Classifier: License :: OSI Approved :: Apache Software License
Classifier: Operating System :: POSIX :: Linux
Classifier: Programming Language :: Python
Classifier: Programming Language :: Python :: 2
Classifier: Programming Language :: Python :: 2.7
Classifier: Programming Language :: Python :: 3
Classifier: Programming Language :: Python :: 3.5
Classifier: Topic :: System :: Monitoring
Requires-Dist: gnocchiclient (>=4.0.0)
Requires-Dist: keystoneauth1
